{
  "releases": [
    {
      "version": "2.198.0-r0",
      "releaseTimestamp": "2026-06-25T15:21:30Z"
    },
    {
      "version": "2.197.0-r1",
      "releaseTimestamp": "2026-06-20T22:57:13Z"
    },
    {
      "version": "2.197.0-r0",
      "releaseTimestamp": "2026-05-28T22:29:13Z"
    },
    {
      "version": "2.196.0-r0",
      "releaseTimestamp": "2026-05-07T04:07:22Z"
    },
    {
      "version": "2.195.0-r0",
      "releaseTimestamp": "2026-05-01T00:07:06Z"
    },
    {
      "version": "2.194.0-r0",
      "releaseTimestamp": "2026-04-08T23:17:35Z"
    },
    {
      "version": "2.193.0-r0",
      "releaseTimestamp": "2026-03-17T21:10:12Z"
    },
    {
      "version": "2.192.0-r0",
      "releaseTimestamp": "2026-03-05T18:08:32Z"
    },
    {
      "version": "2.191.0-r0",
      "releaseTimestamp": "2026-03-02T18:30:16Z"
    },
    {
      "version": "2.190.0-r0",
      "releaseTimestamp": "2026-02-12T04:30:28Z"
    },
    {
      "version": "2.189.0-r0",
      "releaseTimestamp": "2026-02-04T02:51:19Z"
    },
    {
      "version": "2.188.0-r0",
      "releaseTimestamp": "2026-01-13T22:29:33Z"
    }
  ],
  "sourceUrl": "https://github.com/wolfi-dev/os"
}
