{
  "releases": [
    {
      "version": "26.1.2-r4",
      "releaseTimestamp": "2026-05-10T01:49:32Z"
    },
    {
      "version": "26.1.2-r3",
      "releaseTimestamp": "2026-05-08T23:24:32Z"
    },
    {
      "version": "26.1.2-r2",
      "releaseTimestamp": "2026-04-26T01:15:07Z"
    },
    {
      "version": "26.1.2-r1",
      "releaseTimestamp": "2026-04-23T16:03:50Z"
    },
    {
      "version": "26.1.2-r0",
      "releaseTimestamp": "2026-04-03T18:20:19Z"
    }
  ],
  "sourceUrl": "https://github.com/wolfi-dev/os"
}
