{
  "releases": [
    {
      "version": "0.7.0-r35",
      "releaseTimestamp": "2026-07-09T00:13:45Z"
    },
    {
      "version": "0.7.0-r34",
      "releaseTimestamp": "2026-06-17T21:43:28Z"
    },
    {
      "version": "0.7.0-r33",
      "releaseTimestamp": "2026-06-05T10:39:29Z"
    },
    {
      "version": "0.7.0-r32",
      "releaseTimestamp": "2026-05-08T08:04:32Z"
    },
    {
      "version": "0.7.0-r31",
      "releaseTimestamp": "2026-04-11T05:01:09Z"
    },
    {
      "version": "0.7.0-r30",
      "releaseTimestamp": "2026-03-08T20:42:35Z"
    },
    {
      "version": "0.7.0-r29",
      "releaseTimestamp": "2026-02-10T14:29:47Z"
    },
    {
      "version": "0.7.0-r28",
      "releaseTimestamp": "2026-01-31T02:20:00Z"
    }
  ],
  "sourceUrl": "https://github.com/wolfi-dev/os"
}
