{
  "releases": [
    {
      "version": "20260413-r0",
      "releaseTimestamp": "2026-04-17T19:14:14Z"
    },
    {
      "version": "20251003-r4",
      "releaseTimestamp": "2026-03-10T16:59:21Z"
    },
    {
      "version": "20251003-r3",
      "releaseTimestamp": "2026-01-30T05:36:52Z"
    },
    {
      "version": "20251003-r2",
      "releaseTimestamp": "2026-01-13T10:02:45Z"
    },
    {
      "version": "20251003-r1",
      "releaseTimestamp": "2026-01-08T21:07:44Z"
    },
    {
      "version": "20250911-r0",
      "releaseTimestamp": "2025-10-13T16:26:56Z"
    },
    {
      "version": "20250619-r4",
      "releaseTimestamp": "2025-07-29T19:59:26Z"
    }
  ],
  "sourceUrl": "https://github.com/wolfi-dev/os"
}
